fds/__init__.py
fds/sdk/__init__.py
fds/sdk/IRNContacts/__init__.py
fds/sdk/IRNContacts/api_client.py
fds/sdk/IRNContacts/configuration.py
fds/sdk/IRNContacts/exceptions.py
fds/sdk/IRNContacts/model_utils.py
fds/sdk/IRNContacts/rest.py
fds/sdk/IRNContacts/api/__init__.py
fds/sdk/IRNContacts/api/contacts___relationships_api.py
fds/sdk/IRNContacts/api/contacts_api.py
fds/sdk/IRNContacts/apis/__init__.py
fds/sdk/IRNContacts/model/__init__.py
fds/sdk/IRNContacts/model/alternative_email_address_dto.py
fds/sdk/IRNContacts/model/contact_address_dto.py
fds/sdk/IRNContacts/model/contact_custom_field_option_value_dto.py
fds/sdk/IRNContacts/model/contact_custom_field_value_dto.py
fds/sdk/IRNContacts/model/contact_custom_field_value_save_dto.py
fds/sdk/IRNContacts/model/contact_dto.py
fds/sdk/IRNContacts/model/contact_event_dto.py
fds/sdk/IRNContacts/model/contact_event_update_dto.py
fds/sdk/IRNContacts/model/contact_id_name_dto.py
fds/sdk/IRNContacts/model/contact_phone_dto.py
fds/sdk/IRNContacts/model/contact_phone_save_dto.py
fds/sdk/IRNContacts/model/contact_relationship_dto.py
fds/sdk/IRNContacts/model/contact_relationship_save_dto.py
fds/sdk/IRNContacts/model/contact_relationship_two_sided_dto.py
fds/sdk/IRNContacts/model/contact_relationship_two_sided_save_dto.py
fds/sdk/IRNContacts/model/contact_role_dto.py
fds/sdk/IRNContacts/model/contact_save_dto.py
fds/sdk/IRNContacts/model/contact_summary_dto.py
fds/sdk/IRNContacts/model/contact_type_dto.py
fds/sdk/IRNContacts/model/employer_dto.py
fds/sdk/IRNContacts/model/new_item_dto.py
fds/sdk/IRNContacts/model/operation.py
fds/sdk/IRNContacts/model/operation_type.py
fds/sdk/IRNContacts/model/phone_number_type_dto.py
fds/sdk/IRNContacts/model/problem_details.py
fds/sdk/IRNContacts/model/record_preview_dto.py
fds/sdk/IRNContacts/model/relationship_category_id_name_dto.py
fds/sdk/IRNContacts/model/relationship_id_name_dto.py
fds/sdk/IRNContacts/model/relationship_symbol_summary_dto.py
fds/sdk/IRNContacts/model/symbol_type.py
fds.sdk.IRNContacts-1.1.2.dist-info/LICENSE
fds.sdk.IRNContacts-1.1.2.dist-info/METADATA
fds.sdk.IRNContacts-1.1.2.dist-info/WHEEL
fds.sdk.IRNContacts-1.1.2.dist-info/top_level.txt
fds.sdk.IRNContacts-1.1.2.dist-info/RECORD
